pyespresso/__init__.py
pyespresso-0.1.dist-info/METADATA
pyespresso-0.1.dist-info/RECORD
pyespresso-0.1.dist-info/WHEEL
pyespresso-0.1.dist-info/top_level.txt
